HLAQuant/HLAQuant.py
HLAQuant/__init__.py
HLAQuant/__main__.py
HLAQuant/mhc_G_domain.py
HLAQuant/data/hla_nuc.fasta
HLAQuant/data/blastdb/G_ALPHA.fasta
HLAQuant/data/blastdb/G_ALPHA.fasta.phr
HLAQuant/data/blastdb/G_ALPHA.fasta.pin
HLAQuant/data/blastdb/G_ALPHA.fasta.psq
HLAQuant/data/blastdb/G_ALPHA1.fasta
HLAQuant/data/blastdb/G_ALPHA1.fasta.phr
HLAQuant/data/blastdb/G_ALPHA1.fasta.pin
HLAQuant/data/blastdb/G_ALPHA1.fasta.psq
HLAQuant/data/blastdb/G_ALPHA2.fasta
HLAQuant/data/blastdb/G_ALPHA2.fasta.phr
HLAQuant/data/blastdb/G_ALPHA2.fasta.pin
HLAQuant/data/blastdb/G_ALPHA2.fasta.psq
HLAQuant/data/blastdb/G_BETA.fasta
HLAQuant/data/blastdb/G_BETA.fasta.phr
HLAQuant/data/blastdb/G_BETA.fasta.pin
HLAQuant/data/blastdb/G_BETA.fasta.psq
HLAQuant/data/blastdb/IMGT_G_domain_Species.fasta
HLAQuant/data/blastdb/IMGT_G_domain_Species.fasta.phr
HLAQuant/data/blastdb/IMGT_G_domain_Species.fasta.pin
HLAQuant/data/blastdb/IMGT_G_domain_Species.fasta.psq
HLAQuant/data/blastdb/b2m.fasta
HLAQuant/data/blastdb/b2m.fasta.phr
HLAQuant/data/blastdb/b2m.fasta.pin
HLAQuant/data/blastdb/b2m.fasta.psq
HLAQuant/data/blastdb/test.out
HLAQuant/data/blastdb/test_alpha.out
HLAQuant/data/blastdb/test_alpha1.out
HLAQuant/data/blastdb/test_alpha2.out
HLAQuant/data/blastdb/test_beta.out
HLAQuant/data/salmon-0.11.2-linux_x86_64/sample_data.tgz
HLAQuant/test_data/test.txt
HLAQuant/test_data/test_fq.txt
hlaquant-0.0.2.dist-info/LICENSE
hlaquant-0.0.2.dist-info/METADATA
hlaquant-0.0.2.dist-info/WHEEL
hlaquant-0.0.2.dist-info/top_level.txt
hlaquant-0.0.2.dist-info/RECORD
