Metadata-Version: 2.1
Name: hlaquant
Version: 0.0.2
Summary: HLAQuant - Get HLA allele specific expression
Home-page: https://github.com/acrinklaw/hlaquant
Author: Austin Crinklaw
Author-email: acrinklaw@lji.org
License: UNKNOWN
Platform: UNKNOWN
Classifier: Programming Language :: Python :: 3
Classifier: License :: OSI Approved :: GNU Affero General Public License v3 or later (AGPLv3+)
Classifier: Operating System :: Unix
Requires-Dist: pandas
Requires-Dist: biopython
